README.md
setup.py
bed/__init__.py
bed/__main__.py
bed/utils.py
bed.egg-info/PKG-INFO
bed.egg-info/SOURCES.txt
bed.egg-info/dependency_links.txt
bed.egg-info/entry_points.txt
bed.egg-info/requires.txt
bed.egg-info/top_level.txt