Metadata-Version: 2.1
Name: bed
Version: 21.5.2020
Summary: A very simple command line Browser Extension Downloader
Home-page: https://github.com/sdushantha/bed
Author: Siddharth Dushantha
Author-email: siddharth.dushantha@gmail.com
License: UNKNOWN
Platform: UNKNOWN
